setup.py
cntcar_aws.egg-info/PKG-INFO
cntcar_aws.egg-info/SOURCES.txt
cntcar_aws.egg-info/dependency_links.txt
cntcar_aws.egg-info/requires.txt
cntcar_aws.egg-info/top_level.txt
cntcar_aws_lib/__init__.py
cntcar_aws_lib/dynamodb.py
cntcar_aws_lib/s3.py
cntcar_aws_lib/secretsmanager.py
cntcar_aws_lib/utils.py