Metadata-Version: 2.1
Name: cntcar-aws
Version: 0.0.8
Summary: Python library for AWS services used in ConectCar projects
Author: Marcos Lemes
Classifier: Development Status :: 3 - Alpha
Classifier: Programming Language :: Python :: 3
Classifier: Programming Language :: Python :: 3.8
